vpscommacc_core/__init__.py
vpscommacc_core/file.py
vpscommacc_core/mix.py
vpscommacc_core/path.py
vpscommacc_core/regexp.py
vpscommacc_core/time.py
vpscommacc_core-1.0.0.dist-info/LICENSE
vpscommacc_core-1.0.0.dist-info/METADATA
vpscommacc_core-1.0.0.dist-info/WHEEL
vpscommacc_core-1.0.0.dist-info/top_level.txt
vpscommacc_core-1.0.0.dist-info/RECORD
